metadata_driver_interface/__init__.py
metadata_driver_interface/constants.py
metadata_driver_interface/data_plugin.py
metadata_driver_interface/driver_interface.py
metadata_driver_interface/exceptions.py
metadata_driver_interface/log.py
metadata_driver_interface/utils.py
metadatadb_driver_interface/__init__.py
metadatadb_driver_interface/constants.py
metadatadb_driver_interface/exceptions.py
metadatadb_driver_interface/metadatadb.py
metadatadb_driver_interface/plugin.py
metadatadb_driver_interface/search_model.py
metadatadb_driver_interface/utils.py
nevermined_metadata_driver_interface-0.4.1.dist-info/LICENSE
nevermined_metadata_driver_interface-0.4.1.dist-info/METADATA
nevermined_metadata_driver_interface-0.4.1.dist-info/NOTICE
nevermined_metadata_driver_interface-0.4.1.dist-info/WHEEL
nevermined_metadata_driver_interface-0.4.1.dist-info/top_level.txt
nevermined_metadata_driver_interface-0.4.1.dist-info/RECORD
